elasticsearch6_dsl/__init__.py
elasticsearch6_dsl/aggs.py
elasticsearch6_dsl/analysis.py
elasticsearch6_dsl/connections.py
elasticsearch6_dsl/document.py
elasticsearch6_dsl/exceptions.py
elasticsearch6_dsl/faceted_search.py
elasticsearch6_dsl/field.py
elasticsearch6_dsl/function.py
elasticsearch6_dsl/index.py
elasticsearch6_dsl/mapping.py
elasticsearch6_dsl/query.py
elasticsearch6_dsl/search.py
elasticsearch6_dsl/serializer.py
elasticsearch6_dsl/update_by_query.py
elasticsearch6_dsl/utils.py
elasticsearch6_dsl/wrappers.py
elasticsearch6_dsl/response/__init__.py
elasticsearch6_dsl/response/aggs.py
elasticsearch6_dsl/response/hit.py
elasticsearch6_dsl-6.4.0.dist-info/AUTHORS
elasticsearch6_dsl-6.4.0.dist-info/LICENSE
elasticsearch6_dsl-6.4.0.dist-info/METADATA
elasticsearch6_dsl-6.4.0.dist-info/WHEEL
elasticsearch6_dsl-6.4.0.dist-info/top_level.txt
elasticsearch6_dsl-6.4.0.dist-info/RECORD
