Metadata-Version: 2.1
Name: elasticsearch6-dsl
Version: 6.4.0
Summary: Python client for Elasticsearch
Home-page: https://github.com/elasticsearch/elasticsearch-dsl-py
Author: Honza Král
Author-email: honza.kral@gmail.com
License: Apache License, Version 2.0
Platform: UNKNOWN
Classifier: Development Status :: 4 - Beta
Classifier: License :: OSI Approved :: Apache Software License
Classifier: Intended Audience :: Developers
Classifier: Operating System :: OS Independent
Classifier: Programming Language :: Python
Classifier: Programming Language :: Python :: 2
Classifier: Programming Language :: Python :: 2.6
Classifier: Programming Language :: Python :: 2.7
Classifier: Programming Language :: Python :: 3
Classifier: Programming Language :: Python :: 3.2
Classifier: Programming Language :: Python :: 3.3
Classifier: Programming Language :: Python :: 3.4
Classifier: Programming Language :: Python :: 3.5
Classifier: Programming Language :: Python :: 3.6
Classifier: Programming Language :: Python :: Implementation :: CPython
Classifier: Programming Language :: Python :: Implementation :: PyPy
Requires-Dist: elasticsearch6 (<7.0.0,>=6.0.0)
Requires-Dist: python-dateutil
Requires-Dist: six
Requires-Dist: ipaddress ; python_version < "3.3"
Provides-Extra: develop
Requires-Dist: coverage (<5.0.0) ; extra == 'develop'
Requires-Dist: mock ; extra == 'develop'
Requires-Dist: pytest-cov ; extra == 'develop'
Requires-Dist: pytest (>=3.0.0) ; extra == 'develop'
Requires-Dist: pytz ; extra == 'develop'
Requires-Dist: sphinx ; extra == 'develop'
Requires-Dist: sphinx-rtd-theme ; extra == 'develop'
